docxtpl/__init__.py
docxtpl/__main__.py
docxtpl/inline_image.py
docxtpl/listing.py
docxtpl/richtext.py
docxtpl/subdoc.py
docxtpl/template.py
ogdocxtpl-0.16.7.dist-info/LICENSE.txt
ogdocxtpl-0.16.7.dist-info/METADATA
ogdocxtpl-0.16.7.dist-info/WHEEL
ogdocxtpl-0.16.7.dist-info/eager_resources.txt
ogdocxtpl-0.16.7.dist-info/top_level.txt
ogdocxtpl-0.16.7.dist-info/RECORD
