Metadata-Version: 2.1
Name: ogdocxtpl
Version: 0.16.7
Summary: Python docx template engine
Home-page: https://github.com/elapouya/python-docx-template
Author: Eric Lapouyade
License: LGPL 2.1
Keywords: jinja2
Classifier: Intended Audience :: Developers
Classifier: Development Status :: 4 - Beta
Classifier: Programming Language :: Python :: 2
Classifier: Programming Language :: Python :: 2.7
Classifier: Programming Language :: Python :: 3
Classifier: Programming Language :: Python :: 3.4
License-File: LICENSE.txt
Requires-Dist: six
Requires-Dist: python-docx ==0.8.11
Requires-Dist: docxcompose
Requires-Dist: jinja2
Requires-Dist: lxml
Provides-Extra: docs
Requires-Dist: Sphinx ; extra == 'docs'
Requires-Dist: sphinxcontrib-napoleon ; extra == 'docs'
